{
    "2025-09-29_11-15-48_506": {
        "frame_idx": 0,
        "label": null,
        "conf": 0.0
    },
    "2025-09-29_11-15-48_550": {
        "frame_idx": 1,
        "label": null,
        "conf": 0.0
    },
    "2025-09-29_11-15-48_579": {
        "frame_idx": 2,
        "label": null,
        "conf": 0.0
    },
    "2025-09-29_11-15-48_609": {
        "frame_idx": 3,
        "label": null,
        "conf": 0.0
    },
    "2025-09-29_11-15-48_635": {
        "frame_idx": 4,
        "label": null,
        "conf": 0.0
    },
    "2025-09-29_11-15-48_661": {
        "frame_idx": 5,
        "label": "Paper",
        "conf": 0.37658751010894775
    },
    "2025-09-29_11-15-48_688": {
        "frame_idx": 6,
        "label": null,
        "conf": 0.0
    },
    "2025-09-29_11-15-48_713": {
        "frame_idx": 7,
        "label": null,
        "conf": 0.0
    },
    "2025-09-29_11-15-48_740": {
        "frame_idx": 8,
        "label": null,
        "conf": 0.0
    },
    "2025-09-29_11-15-48_766": {
        "frame_idx": 9,
        "label": null,
        "conf": 0.0
    },
    "2025-09-29_11-15-48_793": {
        "frame_idx": 10,
        "label": null,
        "conf": 0.0
    },
    "2025-09-29_11-15-48_818": {
        "frame_idx": 11,
        "label": null,
        "conf": 0.0
    },
    "2025-09-29_11-15-48_844": {
        "frame_idx": 12,
        "label": null,
        "conf": 0.0
    },
    "2025-09-29_11-15-48_868": {
        "frame_idx": 13,
        "label": null,
        "conf": 0.0
    },
    "2025-09-29_11-15-48_894": {
        "frame_idx": 14,
        "label": null,
        "conf": 0.0
    },
    "2025-09-29_11-15-48_919": {
        "frame_idx": 15,
        "label": null,
        "conf": 0.0
    },
    "2025-09-29_11-15-48_944": {
        "frame_idx": 16,
        "label": null,
        "conf": 0.0
    },
    "2025-09-29_11-15-48_970": {
        "frame_idx": 17,
        "label": null,
        "conf": 0.0
    },
    "2025-09-29_11-15-48_996": {
        "frame_idx": 18,
        "label": null,
        "conf": 0.0
    },
    "2025-09-29_11-15-49_021": {
        "frame_idx": 19,
        "label": null,
        "conf": 0.0
    },
    "2025-09-29_11-15-49_047": {
        "frame_idx": 20,
        "label": null,
        "conf": 0.0
    },
    "2025-09-29_11-15-49_071": {
        "frame_idx": 21,
        "label": null,
        "conf": 0.0
    },
    "2025-09-29_11-15-49_098": {
        "frame_idx": 22,
        "label": null,
        "conf": 0.0
    },
    "2025-09-29_11-15-49_124": {
        "frame_idx": 23,
        "label": null,
        "conf": 0.0
    },
    "2025-09-29_11-15-49_152": {
        "frame_idx": 24,
        "label": null,
        "conf": 0.0
    },
    "2025-09-29_11-15-49_179": {
        "frame_idx": 25,
        "label": null,
        "conf": 0.0
    },
    "2025-09-29_11-15-49_207": {
        "frame_idx": 26,
        "label": null,
        "conf": 0.0
    },
    "2025-09-29_11-15-49_236": {
        "frame_idx": 27,
        "label": null,
        "conf": 0.0
    },
    "2025-09-29_11-15-49_264": {
        "frame_idx": 28,
        "label": null,
        "conf": 0.0
    },
    "2025-09-29_11-15-49_292": {
        "frame_idx": 29,
        "label": null,
        "conf": 0.0
    },
    "2025-09-29_11-15-49_318": {
        "frame_idx": 30,
        "label": null,
        "conf": 0.0
    },
    "2025-09-29_11-15-49_343": {
        "frame_idx": 31,
        "label": null,
        "conf": 0.0
    },
    "2025-09-29_11-15-49_370": {
        "frame_idx": 32,
        "label": null,
        "conf": 0.0
    },
    "2025-09-29_11-15-49_395": {
        "frame_idx": 33,
        "label": null,
        "conf": 0.0
    },
    "2025-09-29_11-15-49_420": {
        "frame_idx": 34,
        "label": null,
        "conf": 0.0
    },
    "2025-09-29_11-15-49_445": {
        "frame_idx": 35,
        "label": null,
        "conf": 0.0
    },
    "2025-09-29_11-15-49_470": {
        "frame_idx": 36,
        "label": null,
        "conf": 0.0
    },
    "2025-09-29_11-15-49_494": {
        "frame_idx": 37,
        "label": null,
        "conf": 0.0
    },
    "2025-09-29_11-15-49_520": {
        "frame_idx": 38,
        "label": null,
        "conf": 0.0
    },
    "2025-09-29_11-15-49_545": {
        "frame_idx": 39,
        "label": null,
        "conf": 0.0
    },
    "2025-09-29_11-15-49_571": {
        "frame_idx": 40,
        "label": null,
        "conf": 0.0
    },
    "2025-09-29_11-15-49_596": {
        "frame_idx": 41,
        "label": "Rock",
        "conf": 0.3762442469596863
    },
    "2025-09-29_11-15-49_622": {
        "frame_idx": 42,
        "label": "Rock",
        "conf": 0.6829172372817993
    },
    "2025-09-29_11-15-49_650": {
        "frame_idx": 43,
        "label": "Rock",
        "conf": 0.8735342621803284
    },
    "2025-09-29_11-15-49_678": {
        "frame_idx": 44,
        "label": "Rock",
        "conf": 0.4316500723361969
    },
    "2025-09-29_11-15-49_707": {
        "frame_idx": 45,
        "label": "Rock",
        "conf": 0.8566825985908508
    },
    "2025-09-29_11-15-49_735": {
        "frame_idx": 46,
        "label": "Rock",
        "conf": 0.9088876843452454
    },
    "2025-09-29_11-15-49_765": {
        "frame_idx": 47,
        "label": "Rock",
        "conf": 0.9268150925636292
    },
    "2025-09-29_11-15-49_796": {
        "frame_idx": 48,
        "label": "Rock",
        "conf": 0.9006622433662415
    },
    "2025-09-29_11-15-49_822": {
        "frame_idx": 49,
        "label": "Rock",
        "conf": 0.7406749129295349
    },
    "2025-09-29_11-15-49_852": {
        "frame_idx": 50,
        "label": "Rock",
        "conf": 0.810358464717865
    },
    "2025-09-29_11-15-49_880": {
        "frame_idx": 51,
        "label": "Rock",
        "conf": 0.8883227109909058
    },
    "2025-09-29_11-15-49_910": {
        "frame_idx": 52,
        "label": "Rock",
        "conf": 0.7181928753852844
    },
    "2025-09-29_11-15-49_942": {
        "frame_idx": 53,
        "label": "Rock",
        "conf": 0.9224854111671448
    },
    "2025-09-29_11-15-49_972": {
        "frame_idx": 54,
        "label": "Rock",
        "conf": 0.8653696775436401
    },
    "2025-09-29_11-15-50_002": {
        "frame_idx": 55,
        "label": "Rock",
        "conf": 0.2531571686267853
    },
    "2025-09-29_11-15-50_032": {
        "frame_idx": 56,
        "label": "Rock",
        "conf": 0.8631108403205872
    },
    "2025-09-29_11-15-50_063": {
        "frame_idx": 57,
        "label": "Rock",
        "conf": 0.9061253070831299
    },
    "2025-09-29_11-15-50_093": {
        "frame_idx": 58,
        "label": null,
        "conf": 0.0
    },
    "2025-09-29_11-15-50_122": {
        "frame_idx": 59,
        "label": "Rock",
        "conf": 0.7703664302825928
    },
    "2025-09-29_11-15-50_155": {
        "frame_idx": 60,
        "label": null,
        "conf": 0.0
    },
    "2025-09-29_11-15-50_184": {
        "frame_idx": 61,
        "label": null,
        "conf": 0.0
    },
    "2025-09-29_11-15-50_213": {
        "frame_idx": 62,
        "label": null,
        "conf": 0.0
    },
    "2025-09-29_11-15-50_242": {
        "frame_idx": 63,
        "label": null,
        "conf": 0.0
    },
    "2025-09-29_11-15-50_272": {
        "frame_idx": 64,
        "label": null,
        "conf": 0.0
    },
    "2025-09-29_11-15-50_299": {
        "frame_idx": 65,
        "label": null,
        "conf": 0.0
    },
    "2025-09-29_11-15-50_328": {
        "frame_idx": 66,
        "label": null,
        "conf": 0.0
    },
    "2025-09-29_11-15-50_356": {
        "frame_idx": 67,
        "label": null,
        "conf": 0.0
    },
    "2025-09-29_11-15-50_384": {
        "frame_idx": 68,
        "label": null,
        "conf": 0.0
    },
    "2025-09-29_11-15-50_413": {
        "frame_idx": 69,
        "label": "Rock",
        "conf": 0.776732325553894
    },
    "2025-09-29_11-15-50_443": {
        "frame_idx": 70,
        "label": "Rock",
        "conf": 0.922516942024231
    },
    "2025-09-29_11-15-50_471": {
        "frame_idx": 71,
        "label": null,
        "conf": 0.0
    },
    "2025-09-29_11-15-50_499": {
        "frame_idx": 72,
        "label": "Rock",
        "conf": 0.6183944344520569
    },
    "2025-09-29_11-15-50_526": {
        "frame_idx": 73,
        "label": null,
        "conf": 0.0
    },
    "2025-09-29_11-15-50_554": {
        "frame_idx": 74,
        "label": "Rock",
        "conf": 0.9185445308685303
    },
    "2025-09-29_11-15-50_584": {
        "frame_idx": 75,
        "label": "Rock",
        "conf": 0.9147877097129822
    },
    "2025-09-29_11-15-50_612": {
        "frame_idx": 76,
        "label": "Rock",
        "conf": 0.9139852523803711
    },
    "2025-09-29_11-15-50_640": {
        "frame_idx": 77,
        "label": "Rock",
        "conf": 0.9184885025024414
    },
    "2025-09-29_11-15-50_667": {
        "frame_idx": 78,
        "label": "Rock",
        "conf": 0.8686652183532715
    },
    "2025-09-29_11-15-50_696": {
        "frame_idx": 79,
        "label": null,
        "conf": 0.0
    },
    "2025-09-29_11-15-50_723": {
        "frame_idx": 80,
        "label": null,
        "conf": 0.0
    },
    "2025-09-29_11-15-50_749": {
        "frame_idx": 81,
        "label": "Rock",
        "conf": 0.9062190651893616
    },
    "2025-09-29_11-15-50_777": {
        "frame_idx": 82,
        "label": "Rock",
        "conf": 0.9337320923805237
    },
    "2025-09-29_11-15-50_805": {
        "frame_idx": 83,
        "label": "Rock",
        "conf": 0.9163157939910889
    },
    "2025-09-29_11-15-50_834": {
        "frame_idx": 84,
        "label": "Rock",
        "conf": 0.9231607913970947
    },
    "2025-09-29_11-15-50_860": {
        "frame_idx": 85,
        "label": "Rock",
        "conf": 0.883034884929657
    },
    "2025-09-29_11-15-50_889": {
        "frame_idx": 86,
        "label": "Scissors",
        "conf": 0.6489009857177734
    },
    "2025-09-29_11-15-50_919": {
        "frame_idx": 87,
        "label": "Rock",
        "conf": 0.8962929248809814
    },
    "2025-09-29_11-15-50_948": {
        "frame_idx": 88,
        "label": "Rock",
        "conf": 0.8396884202957153
    },
    "2025-09-29_11-15-50_976": {
        "frame_idx": 89,
        "label": null,
        "conf": 0.0
    },
    "2025-09-29_11-15-51_003": {
        "frame_idx": 90,
        "label": null,
        "conf": 0.0
    },
    "2025-09-29_11-15-51_030": {
        "frame_idx": 91,
        "label": null,
        "conf": 0.0
    },
    "2025-09-29_11-15-51_058": {
        "frame_idx": 92,
        "label": null,
        "conf": 0.0
    },
    "2025-09-29_11-15-51_089": {
        "frame_idx": 93,
        "label": null,
        "conf": 0.0
    },
    "2025-09-29_11-15-51_121": {
        "frame_idx": 94,
        "label": null,
        "conf": 0.0
    },
    "2025-09-29_11-15-51_154": {
        "frame_idx": 95,
        "label": null,
        "conf": 0.0
    },
    "2025-09-29_11-15-51_187": {
        "frame_idx": 96,
        "label": null,
        "conf": 0.0
    },
    "2025-09-29_11-15-51_218": {
        "frame_idx": 97,
        "label": null,
        "conf": 0.0
    },
    "2025-09-29_11-15-51_251": {
        "frame_idx": 98,
        "label": null,
        "conf": 0.0
    },
    "2025-09-29_11-15-51_284": {
        "frame_idx": 99,
        "label": "Rock",
        "conf": 0.6052910685539246
    },
    "2025-09-29_11-15-51_319": {
        "frame_idx": 100,
        "label": null,
        "conf": 0.0
    },
    "2025-09-29_11-15-51_353": {
        "frame_idx": 101,
        "label": "Rock",
        "conf": 0.9061439633369446
    },
    "2025-09-29_11-15-51_389": {
        "frame_idx": 102,
        "label": "Rock",
        "conf": 0.4758991599082947
    },
    "2025-09-29_11-15-51_424": {
        "frame_idx": 103,
        "label": "Rock",
        "conf": 0.8246739506721497
    },
    "2025-09-29_11-15-51_460": {
        "frame_idx": 104,
        "label": "Rock",
        "conf": 0.930932879447937
    },
    "2025-09-29_11-15-51_488": {
        "frame_idx": 105,
        "label": "Rock",
        "conf": 0.913914680480957
    },
    "2025-09-29_11-15-51_517": {
        "frame_idx": 106,
        "label": "Rock",
        "conf": 0.9119723439216614
    },
    "2025-09-29_11-15-51_544": {
        "frame_idx": 107,
        "label": "Rock",
        "conf": 0.9224931001663208
    },
    "2025-09-29_11-15-51_572": {
        "frame_idx": 108,
        "label": "Rock",
        "conf": 0.9087629318237305
    },
    "2025-09-29_11-15-51_600": {
        "frame_idx": 109,
        "label": "Rock",
        "conf": 0.7332944273948669
    },
    "2025-09-29_11-15-51_629": {
        "frame_idx": 110,
        "label": "Rock",
        "conf": 0.661905825138092
    },
    "2025-09-29_11-15-51_657": {
        "frame_idx": 111,
        "label": "Rock",
        "conf": 0.8289220333099365
    },
    "2025-09-29_11-15-51_684": {
        "frame_idx": 112,
        "label": "Rock",
        "conf": 0.8133917450904846
    },
    "2025-09-29_11-15-51_712": {
        "frame_idx": 113,
        "label": "Rock",
        "conf": 0.9024654626846313
    },
    "2025-09-29_11-15-51_740": {
        "frame_idx": 114,
        "label": "Rock",
        "conf": 0.9257807731628418
    },
    "2025-09-29_11-15-51_769": {
        "frame_idx": 115,
        "label": "Rock",
        "conf": 0.9068242907524109
    },
    "2025-09-29_11-15-51_797": {
        "frame_idx": 116,
        "label": "Rock",
        "conf": 0.936400830745697
    },
    "2025-09-29_11-15-51_825": {
        "frame_idx": 117,
        "label": "Rock",
        "conf": 0.9298838973045349
    },
    "2025-09-29_11-15-51_853": {
        "frame_idx": 118,
        "label": "Rock",
        "conf": 0.8870974183082581
    },
    "2025-09-29_11-15-51_881": {
        "frame_idx": 119,
        "label": "Rock",
        "conf": 0.8444414734840393
    },
    "2025-09-29_11-15-51_909": {
        "frame_idx": 120,
        "label": "Rock",
        "conf": 0.8806881904602051
    },
    "2025-09-29_11-15-51_936": {
        "frame_idx": 121,
        "label": "Rock",
        "conf": 0.36696404218673706
    },
    "2025-09-29_11-15-51_966": {
        "frame_idx": 122,
        "label": "Rock",
        "conf": 0.3306114375591278
    },
    "2025-09-29_11-15-51_995": {
        "frame_idx": 123,
        "label": null,
        "conf": 0.0
    },
    "2025-09-29_11-15-52_023": {
        "frame_idx": 124,
        "label": null,
        "conf": 0.0
    },
    "2025-09-29_11-15-52_049": {
        "frame_idx": 125,
        "label": null,
        "conf": 0.0
    },
    "2025-09-29_11-15-52_078": {
        "frame_idx": 126,
        "label": null,
        "conf": 0.0
    },
    "2025-09-29_11-15-52_107": {
        "frame_idx": 127,
        "label": null,
        "conf": 0.0
    },
    "2025-09-29_11-15-52_136": {
        "frame_idx": 128,
        "label": null,
        "conf": 0.0
    },
    "2025-09-29_11-15-52_162": {
        "frame_idx": 129,
        "label": null,
        "conf": 0.0
    },
    "2025-09-29_11-15-52_192": {
        "frame_idx": 130,
        "label": null,
        "conf": 0.0
    },
    "2025-09-29_11-15-52_221": {
        "frame_idx": 131,
        "label": null,
        "conf": 0.0
    },
    "2025-09-29_11-15-52_249": {
        "frame_idx": 132,
        "label": null,
        "conf": 0.0
    },
    "2025-09-29_11-15-52_275": {
        "frame_idx": 133,
        "label": null,
        "conf": 0.0
    },
    "2025-09-29_11-15-52_304": {
        "frame_idx": 134,
        "label": null,
        "conf": 0.0
    },
    "2025-09-29_11-15-52_332": {
        "frame_idx": 135,
        "label": null,
        "conf": 0.0
    },
    "2025-09-29_11-15-52_359": {
        "frame_idx": 136,
        "label": null,
        "conf": 0.0
    },
    "2025-09-29_11-15-52_387": {
        "frame_idx": 137,
        "label": null,
        "conf": 0.0
    },
    "2025-09-29_11-15-52_415": {
        "frame_idx": 138,
        "label": null,
        "conf": 0.0
    },
    "2025-09-29_11-15-52_444": {
        "frame_idx": 139,
        "label": null,
        "conf": 0.0
    },
    "2025-09-29_11-15-52_475": {
        "frame_idx": 140,
        "label": null,
        "conf": 0.0
    },
    "2025-09-29_11-15-52_507": {
        "frame_idx": 141,
        "label": "Rock",
        "conf": 0.7612470984458923
    },
    "2025-09-29_11-15-52_539": {
        "frame_idx": 142,
        "label": "Paper",
        "conf": 0.9148243069648743
    },
    "2025-09-29_11-15-52_573": {
        "frame_idx": 143,
        "label": null,
        "conf": 0.0
    },
    "2025-09-29_11-15-52_607": {
        "frame_idx": 144,
        "label": null,
        "conf": 0.0
    },
    "2025-09-29_11-15-52_635": {
        "frame_idx": 145,
        "label": "Scissors",
        "conf": 0.9111195802688599
    },
    "2025-09-29_11-15-52_667": {
        "frame_idx": 146,
        "label": "Scissors",
        "conf": 0.6481667160987854
    },
    "2025-09-29_11-15-52_705": {
        "frame_idx": 147,
        "label": "Scissors",
        "conf": 0.6221959590911865
    },
    "2025-09-29_11-15-52_736": {
        "frame_idx": 148,
        "label": "Scissors",
        "conf": 0.4478701651096344
    },
    "2025-09-29_11-15-52_765": {
        "frame_idx": 149,
        "label": "Scissors",
        "conf": 0.6573296189308167
    },
    "2025-09-29_11-15-52_795": {
        "frame_idx": 150,
        "label": "Scissors",
        "conf": 0.8103719353675842
    },
    "2025-09-29_11-15-52_825": {
        "frame_idx": 151,
        "label": "Scissors",
        "conf": 0.9154660701751709
    },
    "2025-09-29_11-15-52_853": {
        "frame_idx": 152,
        "label": "Scissors",
        "conf": 0.9180715680122375
    },
    "2025-09-29_11-15-52_882": {
        "frame_idx": 153,
        "label": "Scissors",
        "conf": 0.9209575057029724
    },
    "2025-09-29_11-15-52_914": {
        "frame_idx": 154,
        "label": "Scissors",
        "conf": 0.9157732129096985
    },
    "2025-09-29_11-15-52_944": {
        "frame_idx": 155,
        "label": "Scissors",
        "conf": 0.8910700082778931
    },
    "2025-09-29_11-15-52_975": {
        "frame_idx": 156,
        "label": "Scissors",
        "conf": 0.8969910144805908
    },
    "2025-09-29_11-15-53_007": {
        "frame_idx": 157,
        "label": "Scissors",
        "conf": 0.8036190271377563
    },
    "2025-09-29_11-15-53_037": {
        "frame_idx": 158,
        "label": "Scissors",
        "conf": 0.7348277568817139
    },
    "2025-09-29_11-15-53_068": {
        "frame_idx": 159,
        "label": "Paper",
        "conf": 0.6451541781425476
    },
    "2025-09-29_11-15-53_098": {
        "frame_idx": 160,
        "label": "Scissors",
        "conf": 0.8319647908210754
    },
    "2025-09-29_11-15-53_130": {
        "frame_idx": 161,
        "label": "Scissors",
        "conf": 0.7535504698753357
    },
    "2025-09-29_11-15-53_158": {
        "frame_idx": 162,
        "label": "Scissors",
        "conf": 0.8369355797767639
    },
    "2025-09-29_11-15-53_191": {
        "frame_idx": 163,
        "label": "Scissors",
        "conf": 0.743500828742981
    },
    "2025-09-29_11-15-53_223": {
        "frame_idx": 164,
        "label": "Scissors",
        "conf": 0.6677566766738892
    },
    "2025-09-29_11-15-53_252": {
        "frame_idx": 165,
        "label": "Scissors",
        "conf": 0.7784768342971802
    },
    "2025-09-29_11-15-53_282": {
        "frame_idx": 166,
        "label": "Scissors",
        "conf": 0.8799609541893005
    },
    "2025-09-29_11-15-53_313": {
        "frame_idx": 167,
        "label": "Scissors",
        "conf": 0.8396362662315369
    },
    "2025-09-29_11-15-53_343": {
        "frame_idx": 168,
        "label": "Scissors",
        "conf": 0.8817700147628784
    },
    "2025-09-29_11-15-53_373": {
        "frame_idx": 169,
        "label": "Scissors",
        "conf": 0.8644974827766418
    },
    "2025-09-29_11-15-53_403": {
        "frame_idx": 170,
        "label": "Scissors",
        "conf": 0.8356255888938904
    },
    "2025-09-29_11-15-53_433": {
        "frame_idx": 171,
        "label": "Scissors",
        "conf": 0.690856397151947
    },
    "2025-09-29_11-15-53_463": {
        "frame_idx": 172,
        "label": "Scissors",
        "conf": 0.5357490181922913
    },
    "2025-09-29_11-15-53_493": {
        "frame_idx": 173,
        "label": "Scissors",
        "conf": 0.7565956115722656
    },
    "2025-09-29_11-15-53_525": {
        "frame_idx": 174,
        "label": "Scissors",
        "conf": 0.8046087026596069
    },
    "2025-09-29_11-15-53_556": {
        "frame_idx": 175,
        "label": "Scissors",
        "conf": 0.685308039188385
    },
    "2025-09-29_11-15-53_589": {
        "frame_idx": 176,
        "label": "Scissors",
        "conf": 0.8506742119789124
    },
    "2025-09-29_11-15-53_618": {
        "frame_idx": 177,
        "label": "Scissors",
        "conf": 0.8745499849319458
    },
    "2025-09-29_11-15-53_648": {
        "frame_idx": 178,
        "label": "Scissors",
        "conf": 0.8102229833602905
    },
    "2025-09-29_11-15-53_679": {
        "frame_idx": 179,
        "label": "Scissors",
        "conf": 0.8471404314041138
    },
    "2025-09-29_11-15-53_710": {
        "frame_idx": 180,
        "label": "Scissors",
        "conf": 0.7671149373054504
    },
    "2025-09-29_11-15-53_737": {
        "frame_idx": 181,
        "label": "Scissors",
        "conf": 0.7160080671310425
    },
    "2025-09-29_11-15-53_766": {
        "frame_idx": 182,
        "label": "Scissors",
        "conf": 0.8447046279907227
    },
    "2025-09-29_11-15-53_795": {
        "frame_idx": 183,
        "label": "Scissors",
        "conf": 0.8404328227043152
    },
    "2025-09-29_11-15-53_822": {
        "frame_idx": 184,
        "label": "Scissors",
        "conf": 0.7214456796646118
    },
    "2025-09-29_11-15-53_849": {
        "frame_idx": 185,
        "label": null,
        "conf": 0.0
    },
    "2025-09-29_11-15-53_875": {
        "frame_idx": 186,
        "label": "Scissors",
        "conf": 0.561719536781311
    },
    "2025-09-29_11-15-53_903": {
        "frame_idx": 187,
        "label": "Scissors",
        "conf": 0.8072158694267273
    },
    "2025-09-29_11-15-53_930": {
        "frame_idx": 188,
        "label": "Scissors",
        "conf": 0.3522249758243561
    },
    "2025-09-29_11-15-53_958": {
        "frame_idx": 189,
        "label": "Scissors",
        "conf": 0.5225785970687866
    },
    "2025-09-29_11-15-53_985": {
        "frame_idx": 190,
        "label": "Scissors",
        "conf": 0.824356198310852
    },
    "2025-09-29_11-15-54_012": {
        "frame_idx": 191,
        "label": "Scissors",
        "conf": 0.9092417359352112
    },
    "2025-09-29_11-15-54_040": {
        "frame_idx": 192,
        "label": "Scissors",
        "conf": 0.8570793271064758
    },
    "2025-09-29_11-15-54_068": {
        "frame_idx": 193,
        "label": "Scissors",
        "conf": 0.8715583682060242
    },
    "2025-09-29_11-15-54_097": {
        "frame_idx": 194,
        "label": "Scissors",
        "conf": 0.7368245720863342
    },
    "2025-09-29_11-15-54_125": {
        "frame_idx": 195,
        "label": "Scissors",
        "conf": 0.8592280149459839
    },
    "2025-09-29_11-15-54_153": {
        "frame_idx": 196,
        "label": "Scissors",
        "conf": 0.7884186506271362
    }
}